perfed/__init__.py
perfed/timer.py
perfed/timer_decorator.py
perfed/timer_manager.py
perfed/util.py
perfed-0.1.3.dist-info/METADATA
perfed-0.1.3.dist-info/WHEEL
perfed-0.1.3.dist-info/entry_points.txt
perfed-0.1.3.dist-info/licenses/LICENSE
perfed-0.1.3.dist-info/RECORD
