Metadata-Version: 2.4
Name: perfed
Version: 0.1.3
Summary: A lightweight and convenient package for precise performance timing and analysis in Python.
Project-URL: Homepage, https://github.com/sohenze/perfed
Author-email: Enze Soh <enzesoh@gmail.com>
License-Expression: MIT
License-File: LICENSE
Requires-Python: >=3.12
Requires-Dist: pandas>=2.2.3
Requires-Dist: tabulate>=0.9.0
